setup.py
atay_proba/Binomialdistribution.py
atay_proba/Gaussiandistribution.py
atay_proba/Generaldistribution.py
atay_proba/__init__.py
atay_proba.egg-info/PKG-INFO
atay_proba.egg-info/SOURCES.txt
atay_proba.egg-info/dependency_links.txt
atay_proba.egg-info/not-zip-safe
atay_proba.egg-info/top_level.txt