Metadata-Version: 1.0
Name: atay-proba
Version: 0.1
Summary: Gaussian and binomial distributions
Home-page: UNKNOWN
Author: Ali El Adi
Author-email: alieladi@gmail.com
License: UNKNOWN
Platform: UNKNOWN
